CHANGES.txt
LICENSE.txt
MANIFEST.in
README
README.rst
requirements.txt
setup.py
crispy_forms_registration/__init__.py
crispy_forms_registration/models.py
crispy_forms_registration/tests.py
crispy_forms_registration/urls.py
crispy_forms_registration/forms/__init__.py
crispy_forms_registration/forms/crispy_authentication_form.py
crispy_forms_registration/forms/crispy_password_change_form.py
crispy_forms_registration/forms/crispy_password_reset_form.py
crispy_forms_registration/forms/crispy_registration_form.py
crispy_forms_registration/forms/crispy_set_password_form.py
django_crispy_forms_registration.egg-info/PKG-INFO
django_crispy_forms_registration.egg-info/SOURCES.txt
django_crispy_forms_registration.egg-info/dependency_links.txt
django_crispy_forms_registration.egg-info/requires.txt
django_crispy_forms_registration.egg-info/top_level.txt