Metadata-Version: 1.0
Name: django-crispy-forms-registration
Version: 0.1.1
Summary: Library that merges Django auth, registration, and crispy
Home-page: https://github.com/SoloTodo/django_crispy_forms_registration
Author: Vijay Khemlani
Author-email: vkhemlan@gmail.com
License: LICENSE.txt
Platform: UNKNOWN
